bouillage/__init__.py
bouillage/bouillage.py
bouillage/main.py
bouillage-0.1.2.dist-info/METADATA
bouillage-0.1.2.dist-info/WHEEL
bouillage-0.1.2.dist-info/entry_points.txt
bouillage-0.1.2.dist-info/RECORD
