Metadata-Version: 2.1
Name: bouillage
Version: 0.1.2
Summary: Module de contrôle pour le bouillage de sirop d'érable
Author: elfelip
Author-email: elfelip@yahoo.com
Requires-Python: >=3.12,<4.0
Classifier: Programming Language :: Python :: 3
Classifier: Programming Language :: Python :: 3.12
Requires-Dist: inspqkafka (>=0.9.1,<0.10.0)
Requires-Dist: mock-gpio (>=0.2.0,<0.3.0)
Requires-Dist: rpi-gpio (>=0.7.1,<0.8.0)
